SpikeWizard.py
SpikeWizard-0.0.4.dist-info/LICENSE
SpikeWizard-0.0.4.dist-info/METADATA
SpikeWizard-0.0.4.dist-info/WHEEL
SpikeWizard-0.0.4.dist-info/top_level.txt
SpikeWizard-0.0.4.dist-info/RECORD
