Metadata-Version: 2.1
Name: SpikeWizard
Version: 0.0.4
Summary: SpikeWizard is an advanced Python package designed to automate the process of fitting spikes in raw signals. It offers a comprehensive framework for analyzing signals containing spikes of various types and fitting them to a specified function. SpikeWizard harnesses cutting-edge algorithms and techniques to identify and fit multiple spikes within a signal seamlessly, eliminating the need for manual intervention in setting initial conditions.
Author-email: Andrea Combette <pradyun@example.com>
Maintainer-email: Andrea Combette <brett@example.com>
Project-URL: Homepage, https://example.com
Project-URL: Documentation, https://readthedocs.org
Project-URL: Repository, https://github.com/Chatr0uge/SpikeWizard/tree/main
Project-URL: Bug Tracker, https://github.com/Chatr0uge/SpikeWizard/tree/main/issues
Classifier: Programming Language :: Python
Requires-Python: >=3.8
License-File: LICENSE
Requires-Dist: matplotlib
Requires-Dist: numpy
Requires-Dist: scipy
